0 PUSH_GLOBAL max
0 DEF promedio
1 PUSH_LOCAL numero
2 PUSH_LOCAL tam
3 LOAD_CONST 1
4 STORE_FAST tam
5 PUSH_LOCAL resultado
6 LOAD_CONST 0
7 STORE_FAST resultado
8 PUSH_LOCAL sumatoria
9 LOAD_CONST 5
10 STORE_FAST sumatoria
11 LOAD_FAST tam
12 LOAD_CONST 0
13 COMPARE_OP >
14 JUMP_IF_FALSE 19
15 LOAD_FAST sumatoria
16 LOAD_FAST numero
17 BINARY_DIVIDE
18 STORE_FAST resultado
19 LOAD_FAST resultado
20 RETURN_VALUE

21 DEF Main
22 LOAD_CONST 2
00 STORE_GLOBAL max
00 LOAD_GLOBAL max
23 LOAD_GLOBAL promedio
24 CALL_FUNCTION 1
25 LOAD_GLOBAL print
26 CALL_FUNCTION 1
27 END
