0   DEF calcularFac
1 PUSH_LOCAL n
2 PUSH_LOCAL resultado
3 PUSH_LOCAL i
4 LOAD_CONST 1
5 STORE_FAST resultado
6 LOAD_CONST 0
7 STORE_FAST i
8 LOAD_FAST i
9 LOAD_FAST n
10 COMPARE_OP <
11 JUMP_IF_FALSE 23
12 LOAD_FAST resultado
13 LOAD_FAST i
14 LOAD_CONST 1

15 BINARY_ADD
16 BINARY_MULTIPLY
17 STORE_FAST resultado

18 LOAD_FAST i
19 LOAD_CONST 1
20 BINARY_ADD
21 STORE_FAST i
22 JUMP_ABSOLUTE 8
23 LOAD_FAST resultado
24 RETURN_VALUE
25 DEF Main
26 LOAD_CONST "Resultado:"
27 LOAD_GLOBAL print
28 CALL_FUNCTION 1
29 LOAD_CONST 5
30 LOAD_GLOBAL calcularFac
31 CALL_FUNCTION 1
32 LOAD_GLOBAL print
33 CALL_FUNCTION 1
34 END